string_signer/__init__.py
string_signer/exceptions.py
string_signer/main.py
String_Signer-0.1.1.dist-info/LICENSE
String_Signer-0.1.1.dist-info/METADATA
String_Signer-0.1.1.dist-info/WHEEL
String_Signer-0.1.1.dist-info/top_level.txt
String_Signer-0.1.1.dist-info/RECORD
