Metadata-Version: 2.1
Name: String-Signer
Version: 0.1.1
Summary: Used to sign strings.
Home-page: https://github.com/cesarmerjan/string_signer
Author: Cesar Merjan
Author-email: cesarmerjan@gmail.com
License: MIT
Download-URL: https://github.com/cesarmerjan/string_signer/archive/refs/heads/master.zip
Keywords: sign,backend,session,security,signer
Platform: UNKNOWN
Classifier: Development Status :: 4 - Beta
Classifier: License :: OSI Approved :: Apache Software License
Classifier: Intended Audience :: Developers
Classifier: Environment :: Web Environment
Classifier: Topic :: Security
Classifier: Topic :: Security :: Cryptography
Classifier: Topic :: Utilities
Classifier: Topic :: Software Development
Classifier: Topic :: Software Development :: Libraries
Classifier: Topic :: Software Development :: Pre-processors
Classifier: Programming Language :: Python :: 3
Classifier: Programming Language :: Python :: 3 :: Only
Classifier: Programming Language :: Python :: 3.6
Classifier: Programming Language :: Python :: 3.7
Classifier: Programming Language :: Python :: 3.8
Classifier: Operating System :: Unix
Classifier: Operating System :: MacOS :: MacOS X
Classifier: Operating System :: Microsoft :: Windows
Requires-Python: >3.6
